torchlens/__init__.py
torchlens/cleanup.py
torchlens/constants.py
torchlens/decorate_torch.py
torchlens/helper_funcs.py
torchlens/interface.py
torchlens/logging_funcs.py
torchlens/model_funcs.py
torchlens/model_handling.py
torchlens/model_history.py
torchlens/op_logging.py
torchlens/postprocess.py
torchlens/summarize.py
torchlens/tensor_log.py
torchlens/trace_model.py
torchlens/tracing.py
torchlens/ui.py
torchlens/user_funcs.py
torchlens/validation.py
torchlens/vis.py
torchlens-0.1.36.dist-info/LICENSE
torchlens-0.1.36.dist-info/METADATA
torchlens-0.1.36.dist-info/WHEEL
torchlens-0.1.36.dist-info/top_level.txt
torchlens-0.1.36.dist-info/RECORD
