Metadata-Version: 2.1
Name: torchlens
Version: 0.1.36
Summary: A package for extracting activations from PyTorch models
Home-page: https://github.com/johnmarktaylor91/torchlens
Author: JohnMark Taylor
Author-email: johnmarkedwardtaylor@gmail.com
License: GNU GPL v3
Keywords: torch torchlens features
Classifier: Development Status :: 3 - Alpha
Classifier: Intended Audience :: Science/Research
Classifier: License :: OSI Approved :: GNU General Public License v3 (GPLv3)
Classifier: Natural Language :: English
Classifier: Programming Language :: Python :: 3.9
License-File: LICENSE
Requires-Dist: numpy
Requires-Dist: pandas
Requires-Dist: pytest
Requires-Dist: tqdm
Requires-Dist: ipython
Requires-Dist: graphviz
Provides-Extra: dev
Requires-Dist: black[jupyter] ; extra == 'dev'
Requires-Dist: pytest ; extra == 'dev'
Requires-Dist: pre-commit ; extra == 'dev'
